[
  {
    "Author": "The Enceladeum",
    "Name": "HMoniker",
    "InternalName": "HMoniker",
    "Punchline": "Like Honorific, but for names.",
    "Description": "Changes your display name. Local only: visible only to yourself outside of HMS (HMapSync) sessions.",
    "Changelog": "1.0.0: first stable release. Compose your nameplate name from five free-text slots (prefix, first, middle, last, suffix) and optionally hide the free company tag.",
    "Tags": [ "rp", "roleplay", "nameplate", "name", "garlean" ],
    "CategoryTags": [ "other" ],
    "IsHide": false,
    "IsTestingExclusive": false,
    "ApplicableVersion": "any",
    "RepoUrl": "https://github.com/Enceladeum/HMoniker",
    "AssemblyVersion": "1.0.0.0",
    "DalamudApiLevel": 15,
    "LoadRequiredState": 0,
    "LoadSync": false,
    "CanUnloadAsync": false,
    "LoadPriority": 0,
    "AcceptsFeedback": true,
    "DownloadCount": 0,
    "LastUpdate": 1783375996,
    "DownloadLinkInstall": "https://github.com/Enceladeum/HMoniker/releases/latest/download/latest.zip",
    "DownloadLinkUpdate": "https://github.com/Enceladeum/HMoniker/releases/latest/download/latest.zip",
    "DownloadLinkTesting": "https://github.com/Enceladeum/HMoniker/releases/latest/download/latest.zip",
    "IconUrl": "https://raw.githubusercontent.com/Enceladeum/HMoniker/main/images/icon.png"
  }
]
